topsis_101703291/Topsis.py
Topsis_101703291_thapar-1.0.1.dist-info/LICENSE.txt
Topsis_101703291_thapar-1.0.1.dist-info/METADATA
Topsis_101703291_thapar-1.0.1.dist-info/WHEEL
Topsis_101703291_thapar-1.0.1.dist-info/entry_points.txt
Topsis_101703291_thapar-1.0.1.dist-info/top_level.txt
Topsis_101703291_thapar-1.0.1.dist-info/RECORD
